README.rst
setup.py
thoth/__init__.py
thoth.egg-info/PKG-INFO
thoth.egg-info/SOURCES.txt
thoth.egg-info/dependency_links.txt
thoth.egg-info/not-zip-safe
thoth.egg-info/top_level.txt