Metadata-Version: 1.0
Name: thoth
Version: 0.0.1
Summary: Thoth project
Home-page: UNKNOWN
Author: Fridolin Pokorny
Author-email: fridolin@redhat.com
License: GPLv2+
Platform: UNKNOWN
